joffpype/__init__.py
joffpype/infix.py
joffpype/superpipe.py
joffpype/utils.py
joffpype-1.1.0.dist-info/LICENSE.txt
joffpype-1.1.0.dist-info/METADATA
joffpype-1.1.0.dist-info/WHEEL
joffpype-1.1.0.dist-info/top_level.txt
joffpype-1.1.0.dist-info/RECORD
