Metadata-Version: 2.1
Name: joffpype
Version: 1.1.0
Home-page: https://github.com/jfsalzmann/joffpype
Author: Joff
Author-email: mail@jfsalzmann.com
Keywords: "python pipe magrittr r"
Classifier: Programming Language :: Python :: 3
Classifier: License :: OSI Approved :: MIT License
Classifier: Operating System :: OS Independent
Requires-Python: >=3.5
License-File: LICENSE.txt
